dmitlibx/__init__.py
dmitlibx/utils.py
dmitlibx-0.1.0.dist-info/METADATA
dmitlibx-0.1.0.dist-info/WHEEL
dmitlibx-0.1.0.dist-info/top_level.txt
dmitlibx-0.1.0.dist-info/RECORD
